mazeflow/__init__.py
mazeflow/frontier.py
mazeflow/generator.py
mazeflow/search.py
mazeflow/lib/__init__.py
mazeflow-0.0.3.dist-info/LICENSE.md
mazeflow-0.0.3.dist-info/METADATA
mazeflow-0.0.3.dist-info/WHEEL
mazeflow-0.0.3.dist-info/top_level.txt
mazeflow-0.0.3.dist-info/RECORD
